[
    {
        "code": "B17-FF",
        "total_amount": 3711.00,
        "status": "pending"
    },
    {
        "code": "B17-GF",
        "total_amount": 2656.00,
        "status": "pending"
    },
    {
        "code": "B17-SF",
        "total_amount": 2311.00,
        "status": "pending"
    },
    {
        "code": "B18-FF",
        "total_amount": 2311.00,
        "status": "pending"
    },
    {
        "code": "B18-GF",
        "total_amount": 2602.00,
        "status": "pending"
    },
    {
        "code": "B18-SF",
        "total_amount": 2311.00,
        "status": "pending"
    },
    {
        "code": "B5-FF",
        "total_amount": 2311.00,
        "status": "pending"
    },
    {
        "code": "B5-GF",
        "total_amount": 2311.00,
        "status": "pending"
    },
    {
        "code": "B5-SF",
        "total_amount": 2311.00,
        "status": "pending"
    },
    {
        "code": "B6-FF",
        "total_amount": 2311.00,
        "status": "pending"
    },
    {
        "code": "B6-GF",
        "total_amount": 7691.00,
        "status": "pending"
    },
    {
        "code": "B6-SF",
        "total_amount": 2311.00,
        "status": "pending"
    },
    {
        "code": "C10-FF",
        "total_amount": 4189.00,
        "status": "pending"
    },
    {
        "code": "C10-GF",
        "total_amount": 1890.00,
        "status": "pending"
    },
    {
        "code": "C10-SF",
        "total_amount": 1978.00,
        "status": "pending"
    },
    {
        "code": "C11-FF",
        "total_amount": 1890.00,
        "status": "pending"
    },
    {
        "code": "C11-GF",
        "total_amount": 1890.00,
        "status": "pending"
    },
    {
        "code": "C11-SF",
        "total_amount": 1890.00,
        "status": "pending"
    },
    {
        "code": "C14-FF",
        "total_amount": 1890.00,
        "status": "pending"
    },
    {
        "code": "C14-GF",
        "total_amount": 1890.00,
        "status": "pending"
    },
    {
        "code": "C14-SF",
        "total_amount": 5206.00,
        "status": "pending"
    },
    {
        "code": "C15-FF",
        "total_amount": 2995.00,
        "status": "pending"
    },
    {
        "code": "C15-GF",
        "total_amount": 1890.00,
        "status": "pending"
    },
    {
        "code": "C15-SF",
        "total_amount": 1890.00,
        "status": "pending"
    },
    {
        "code": "C16-FF",
        "total_amount": 1890.00,
        "status": "pending"
    },
    {
        "code": "C16-GF",
        "total_amount": 1890.00,
        "status": "pending"
    },
    {
        "code": "C16-SF",
        "total_amount": 1890.00,
        "status": "pending"
    },
    {
        "code": "C17-FF",
        "total_amount": 1890.00,
        "status": "pending"
    },
    {
        "code": "C17-GF",
        "total_amount": 1890.00,
        "status": "pending"
    },
    {
        "code": "C17-SF",
        "total_amount": 1890.00,
        "status": "pending"
    },
    {
        "code": "C8-FF",
        "total_amount": 1890.00,
        "status": "pending"
    },
    {
        "code": "C8-GF",
        "total_amount": 1890.00,
        "status": "pending"
    },
    {
        "code": "C8-SF",
        "total_amount": 1890.00,
        "status": "pending"
    },
    {
        "code": "C9-FF",
        "total_amount": 1890.00,
        "status": "pending"
    },
    {
        "code": "C9-GF",
        "total_amount": 1890.00,
        "status": "pending"
    },
    {
        "code": "C9-SF",
        "total_amount": 1890.00,
        "status": "pending"
    },
    {
        "code": "D1-FF",
        "total_amount": 1735.00,
        "status": "pending"
    },
    {
        "code": "D1-GF",
        "total_amount": 1866.00,
        "status": "pending"
    },
    {
        "code": "D1-SF",
        "total_amount": 2389.00,
        "status": "pending"
    },
    {
        "code": "D10-FF",
        "total_amount": 1474.00,
        "status": "pending"
    },
    {
        "code": "D10-GF",
        "total_amount": 1474.00,
        "status": "pending"
    },
    {
        "code": "D10-SF",
        "total_amount": 1474.00,
        "status": "pending"
    },
    {
        "code": "D11-FF",
        "total_amount": 1474.00,
        "status": "pending"
    },
    {
        "code": "D11-GF",
        "total_amount": 1474.00,
        "status": "pending"
    },
    {
        "code": "D11-SF",
        "total_amount": 1474.00,
        "status": "pending"
    },
    {
        "code": "D2-FF",
        "total_amount": 1474.00,
        "status": "pending"
    },
    {
        "code": "D2-GF",
        "total_amount": 5629.00,
        "status": "pending"
    },
    {
        "code": "D2-SF",
        "total_amount": 1474.00,
        "status": "pending"
    },
    {
        "code": "D3-FF",
        "total_amount": 1474.00,
        "status": "pending"
    },
    {
        "code": "D3-GF",
        "total_amount": 1474.00,
        "status": "pending"
    },
    {
        "code": "D3-SF",
        "total_amount": 1686.00,
        "status": "pending"
    },
    {
        "code": "D4-FF",
        "total_amount": 1474.00,
        "status": "pending"
    },
    {
        "code": "D4-GF",
        "total_amount": 1474.00,
        "status": "pending"
    },
    {
        "code": "D4-SF",
        "total_amount": 2725.00,
        "status": "pending"
    },
    {
        "code": "D6-FF",
        "total_amount": 4616.00,
        "status": "pending"
    },
    {
        "code": "D6-GF",
        "total_amount": 1474.00,
        "status": "pending"
    },
    {
        "code": "D6-SF",
        "total_amount": 2259.00,
        "status": "pending"
    },
    {
        "code": "D7-FF",
        "total_amount": 1474.00,
        "status": "pending"
    },
    {
        "code": "D7-GF",
        "total_amount": 3281.00,
        "status": "pending"
    },
    {
        "code": "D7-SF",
        "total_amount": 1474.00,
        "status": "pending"
    }
]